{
  "$schema": "https://raw.githubusercontent.com/streetsidesoftware/cspell/main/cspell.schema.json",
  "version": "0.2",
  "files": ["**"],
  "enableFiletypes": ["*"],
  "enableGlobDot": true,
  "useGitignore": true,
  "ignorePaths": ["*.svg", ".git/**", ".yarn/**", "LICENSE"],
  "words": [
    "ahming",
    "albertine",
    "animex",
    "antizoubilamaka",
    "aridolomo",
    "asaelr",
    "asddsa",
    "ated",
    "autocrlf",
    "bauza",
    "BCME",
    "blueviolet",
    "cathys",
    "clsx",
    "cluable",
    "cluer",
    "cocktailgames",
    "codenames",
    "corepack",
    "crossorigin",
    "darkgreen",
    "darkred",
    "dbaeumer",
    "deepskyblue",
    "deorsey",
    "depender",
    "derekcheah",
    "desync",
    "desynchronization",
    "desynchronize",
    "desynchronized",
    "dilorenzo",
    "duneaught",
    "esbenp",
    "fireheart",
    "floriman",
    "floris",
    "florrat",
    "gameplay",
    "gentlemans",
    "gtkiwnous",
    "hanab",
    "hanabi",
    "hanabornoob",
    "hideable",
    "iamjeff",
    "iamwhoiamhahaha",
    "incentivized",
    "indego",
    "infima",
    "isaacscript",
    "isdariel",
    "jenn",
    "joelwool",
    "kakashi",
    "keldon",
    "kimbifille",
    "Kunsemiller",
    "letical",
    "lgeiger",
    "libster",
    "lightgreen",
    "lilliana",
    "maxdepth",
    "mcvp",
    "metagame",
    "micerang",
    "misranked",
    "occams",
    "offsetblur",
    "omni",
    "peaceiris",
    "pianoblook",
    "playstyle",
    "PPCL",
    "progressbar",
    "promptable",
    "pyrotechnicians",
    "rainbowtext",
    "ralenti",
    "razvogor",
    "retext",
    "rnrgames",
    "romain",
    "rubbo",
    "rygb",
    "rygbi",
    "rygbp",
    "rygbpi",
    "rygp",
    "sankala",
    "sarisia",
    "scdb",
    "scharkbite",
    "schrödingers",
    "sdcm",
    "sjdrodge",
    "speedruns",
    "starcraft",
    "Sturm",
    "stylelint",
    "sucubis",
    "svgr",
    "svgwrite",
    "tccm",
    "technote",
    "tobin",
    "tocm",
    "uncluable",
    "unclued",
    "unifiedjs",
    "unpromptable",
    "untimed",
    "utpf",
    "uutd",
    "valetta",
    "xdragun",
    "xgtkiwnous",
    "xrbm",
    "xrygb",
    "xrygbi",
    "xrygp",
    "ygbp",
    "zamiel"
  ]
}
